<Keyboard>
	<BorderThickness>1,30,1,1</BorderThickness>
    <Height>32</Height>
   <SymbolMargin>25</SymbolMargin>
   <HideFromKeyboardMenu>True</HideFromKeyboardMenu>
   <InitialKeyStates>
     <KeyUp>MouseMagneticCursor</KeyUp>
     <KeyLockedDown>MouseMagnifier</KeyLockedDown>   
   </InitialKeyStates>
   <Grid>
    <Rows>2</Rows>
    <Cols>8</Cols>
    </Grid>
	<Keys>
		<TextKey>
			<Label>1</Label>
			<Index>0</Index>
			<Text>1</Text>
			<Row>0</Row>
			<Col>0</Col>
			<Height>1</Height>
			<Width>1</Width>
		</TextKey>
		<TextKey>
			<Label>2</Label>
			<Index>1</Index>
			<Text>2</Text>
			<Row>0</Row>
			<Col>1</Col>
			<Height>1</Height>
			<Width>1</Width>
		</TextKey>
		<TextKey>
			<Label>3</Label>
			<Index>2</Index>
			<Text>3</Text>
			<Row>0</Row>
			<Col>2</Col>
			<Height>1</Height>
			<Width>1</Width>
		</TextKey>
		<TextKey>
			<Label>4</Label>
			<Index>3</Index>
			<Text>4</Text>
			<Row>0</Row>
			<Col>3</Col>
			<Height>1</Height>
			<Width>1</Width>
		</TextKey>
		<TextKey>
			<Label>5</Label>
			<Index>4</Index>
			<Text>5</Text>
			<Row>0</Row>
			<Col>4</Col>
			<Height>1</Height>
			<Width>1</Width>
		</TextKey>
		<TextKey>
			<Label>6</Label>
			<Index>5</Index>
			<Text>6</Text>
			<Row>0</Row>
			<Col>5</Col>
			<Height>1</Height>
			<Width>1</Width>
		</TextKey>
		<TextKey>
			<Label>7</Label>
			<Index>6</Index>
			<Text>7</Text>
			<Row>0</Row>
			<Col>6</Col>
			<Height>1</Height>
			<Width>1</Width>
		</TextKey>
		<ActionKey>
			<Label>Esc</Label>
            <Symbol>MinecraftEscButton</Symbol>
			<Index>7</Index>
			<Action>Escape</Action>
			<Row>0</Row>
			<Col>7</Col>
			<Height>1</Height>
			<Width>1</Width>
		</ActionKey>
		<ChangeKeyboardKey>
			<Label></Label>
			<Index>8</Index>
			<Symbol>ArrowPointingToLeftIcon</Symbol>
			<DestinationKeyboard>2_MC_8_2_2.xml</DestinationKeyboard>
			<ReturnToThisKeyboard>False</ReturnToThisKeyboard>
			<Row>1</Row>
			<Col>0</Col>
			<Height>1</Height>
			<Width>1</Width>
		</ChangeKeyboardKey>
		<TextKey>
			<Label>Open\ninventory</Label>
			<Index>9</Index>
			<Text>e</Text>
			<Row>1</Row>
			<Col>1</Col>
			<Height>1</Height>
			<Width>1</Width>
		</TextKey>
		<ActionKey>
			<Label>Prev\ntab</Label>
			<Index>10</Index>
			<Symbol>MinecraftTabPrev</Symbol>
			<Action>ArrowLeft</Action>
			<Row>1</Row>
			<Col>2</Col>
			<Height>1</Height>
			<Width>1</Width>
		</ActionKey>
		<ActionKey>
			<Label>Next\ntab</Label>
			<Index>11</Index>
			<Symbol>MinecraftTabNext</Symbol>
			<Action>ArrowRight</Action>
			<Row>1</Row>
			<Col>3</Col>
			<Height>1</Height>
			<Width>1</Width>
		</ActionKey>
        
        
		<ActionKey>
			<Label>Scroll\ndown</Label>
			<Index>14</Index>
            <Symbol>MouseScrollToBottomIcon</Symbol>
			<Action>MouseScrollToBottom</Action>
			<Row>1</Row>
			<Col>4</Col>
			<Height>1</Height>
			<Width>1</Width>
		</ActionKey>
        
        <ActionKey>
			<Label>Left\nclick</Label>
			<Symbol>MouseLeftClickWithMouseIcon</Symbol>
			<Action>MouseMoveAndLeftClick</Action>
			<Row>1</Row>
			<Col>5</Col>
			<Height>1</Height>
			<Width>1</Width>
		</ActionKey>
        
        <ActionKey>
			<Label>Discard</Label>			
			<Action>Home</Action>
			<Row>1</Row>
			<Col>6</Col>
			<Height>1</Height>
			<Width>1</Width>
		</ActionKey>       
        
        
        <ActionKey>
            <Symbol>BackIcon</Symbol>
			<Action>BackFromKeyboard</Action>
            <Row>1</Row>
			<Col>7</Col>
		</ActionKey>
	</Keys>
</Keyboard>